livekit/plugins/playai/__init__.py
livekit/plugins/playai/log.py
livekit/plugins/playai/models.py
livekit/plugins/playai/py.typed
livekit/plugins/playai/tts.py
livekit/plugins/playai/version.py
livekit_plugins_playai-1.2.15.dist-info/METADATA
livekit_plugins_playai-1.2.15.dist-info/WHEEL
livekit_plugins_playai-1.2.15.dist-info/RECORD
