Metadata-Version: 2.4
Name: livekit-plugins-playai
Version: 1.2.15
Summary: Agent Framework plugin for voice synthesis with PlayAI's API.
Project-URL: Documentation, https://docs.livekit.io
Project-URL: Website, https://livekit.io/
Project-URL: Source, https://github.com/livekit/agents
Author-email: LiveKit <hello@livekit.io>
License-Expression: Apache-2.0
Keywords: audio,livekit,playAI,playHT,realtime,webrtc
Classifier: Intended Audience :: Developers
Classifier: Programming Language :: Python :: 3
Classifier: Programming Language :: Python :: 3 :: Only
Classifier: Programming Language :: Python :: 3.11
Classifier: Programming Language :: Python :: 3.12
Classifier: Topic :: Multimedia :: Sound/Audio
Classifier: Topic :: Scientific/Engineering :: Artificial Intelligence
Requires-Python: >=3.9.0
Requires-Dist: aiohttp
Requires-Dist: livekit
Requires-Dist: livekit-agents[codecs]>=1.2.15
Requires-Dist: pyht>=0.1.14
